diffpanstarrs/__init__.py
diffpanstarrs/alignment.py
diffpanstarrs/command_line.py
diffpanstarrs/config.py
diffpanstarrs/decider.py
diffpanstarrs/differenceImaging.py
diffpanstarrs/getPanSTARRSData.py
diffpanstarrs/imageMoments.py
diffpanstarrs/moffatRemoval.py
diffpanstarrs/pipeline.py
diffpanstarrs/plotting.py
diffpanstarrs/utilities.py
diffpanstarrs/wavelet.py
diffpanstarrs/wcs.py
diffpanstarrs/cnn_weights/model.hdf5
diffpanstarrs/sextractor_defaults/__init__.py
diffpanstarrs/sextractor_defaults/default.conv
diffpanstarrs/sextractor_defaults/default.param
tests/__init__.py
tests/test_decider.py
tests/test_image_moments.py
tests/test_norealtest_match_catalogues.py
tests/test_norealtest_readcatalogue.py
tests/test_penalty_by_residuals.py
tests/test_pipeline.py
tests/test_pipeline_score.py
tests/test_simple_download_and_process.py
tests/test_wavelet.py
diffpanstarrs-0.11.dist-info/LICENSE
diffpanstarrs-0.11.dist-info/METADATA
diffpanstarrs-0.11.dist-info/WHEEL
diffpanstarrs-0.11.dist-info/entry_points.txt
diffpanstarrs-0.11.dist-info/top_level.txt
diffpanstarrs-0.11.dist-info/RECORD
