Metadata-Version: 2.1
Name: diffpanstarrs
Version: 0.11
Summary: Downloads Pan-STARRS data around given coordinates and performs difference imaging to extract light curves
Home-page: UNKNOWN
Author: Frederic Dux, Cameron Lemon
Author-email: frederic.dux@epfl.ch
License: GPL
Platform: UNKNOWN
Requires-Python: >3.7.0
Requires-Dist: urllib3
Requires-Dist: wget
Requires-Dist: numpy
Requires-Dist: scipy
Requires-Dist: astropy
Requires-Dist: matplotlib
Requires-Dist: scikit-image
